ambition_prn/__init__.py
ambition_prn/action_items.py
ambition_prn/admin_site.py
ambition_prn/apps.py
ambition_prn/baker_recipes.py
ambition_prn/choices.py
ambition_prn/constants.py
ambition_prn/list_data.py
ambition_prn/notifications.py
ambition_prn/offline_models.py
ambition_prn/signals.py
ambition_prn/urls.py
ambition_prn/wsgi.py
ambition_prn/admin/__init__.py
ambition_prn/admin/onschedule_admin.py
ambition_prn/admin/onschedule_w10_admin.py
ambition_prn/admin/protocol_deviation_violation_admin.py
ambition_prn/admin/study_termination_conclusion_admin.py
ambition_prn/admin/study_termination_conclusion_w10_admin.py
ambition_prn/form_validators/__init__.py
ambition_prn/form_validators/protocol_deviation_violation.py
ambition_prn/form_validators/study_day_form_validator_mixin.py
ambition_prn/form_validators/study_termination_conclusion.py
ambition_prn/form_validators/study_termination_conclusion_w10.py
ambition_prn/forms/__init__.py
ambition_prn/forms/amphotericin_missed_doses_form.py
ambition_prn/forms/fluconazole_missed_doses_form.py
ambition_prn/forms/flucytosine_missed_doses_form.py
ambition_prn/forms/protocol_deviation_violation_form.py
ambition_prn/forms/significant_diagnoses_form.py
ambition_prn/forms/study_termination_conclusion_form.py
ambition_prn/forms/study_termination_conclusion_w10_form.py
ambition_prn/migrations/0001_initial.py
ambition_prn/migrations/0002_auto_20180119_1312.py
ambition_prn/migrations/0003_auto_20180121_1411.py
ambition_prn/migrations/0004_auto_20180409_1213.py
ambition_prn/migrations/0005_auto_20180708_0925.py
ambition_prn/migrations/0006_auto_20180809_0504.py
ambition_prn/migrations/0007_auto_20181007_0053.py
ambition_prn/migrations/0008_auto_20181007_0103.py
ambition_prn/migrations/0009_auto_20181009_0545.py
ambition_prn/migrations/0010_auto_20181009_1837.py
ambition_prn/migrations/0011_auto_20181009_1838.py
ambition_prn/migrations/0012_auto_20181009_1848.py
ambition_prn/migrations/0013_auto_20181108_0353.py
ambition_prn-0.1.75.dist-info/AUTHORS
ambition_prn-0.1.75.dist-info/LICENSE
ambition_prn-0.1.75.dist-info/METADATA
ambition_prn-0.1.75.dist-info/WHEEL
ambition_prn-0.1.75.dist-info/top_level.txt
ambition_prn-0.1.75.dist-info/RECORD
